{
    "data": [
        {
            "expandId": 1,
            "expandPassiveSkill": [
                23028
            ],
            "expandRandomPassiveSkill": [],
            "randomNum": 0
        },
        {
            "expandId": 2,
            "expandPassiveSkill": [
                23028,
                23029
            ],
            "expandRandomPassiveSkill": [],
            "randomNum": 0
        },
        {
            "expandId": 3,
            "expandPassiveSkill": [
                5110071,
                5110561
            ],
            "expandRandomPassiveSkill": [
                5110071,
                5110561
            ],
            "randomNum": 1
        },
        {
            "expandId": 4,
            "expandPassiveSkill": [
                5110531
            ],
            "expandRandomPassiveSkill": [
                5110071,
                5110561
            ],
            "randomNum": 1
        },
        {
            "expandId": 101,
            "expandPassiveSkill": [
                6000010
            ],
            "expandRandomPassiveSkill": [],
            "randomNum": 0
        },
        {
            "expandId": 102,
            "expandPassiveSkill": [
                6000020
            ],
            "expandRandomPassiveSkill": [],
            "randomNum": 0
        },
        {
            "expandId": 103,
            "expandPassiveSkill": [
                6000030
            ],
            "expandRandomPassiveSkill": [],
            "randomNum": 0
        },
        {
            "expandId": 104,
            "expandPassiveSkill": [
                6000040
            ],
            "expandRandomPassiveSkill": [],
            "randomNum": 0
        },
        {
            "expandId": 201,
            "expandPassiveSkill": [
                6000050
            ],
            "expandRandomPassiveSkill": [],
            "randomNum": 0
        },
        {
            "expandId": 202,
            "expandPassiveSkill": [
                6000060
            ],
            "expandRandomPassiveSkill": [],
            "randomNum": 0
        },
        {
            "expandId": 203,
            "expandPassiveSkill": [
                6000070
            ],
            "expandRandomPassiveSkill": [],
            "randomNum": 0
        },
        {
            "expandId": 204,
            "expandPassiveSkill": [
                6000080
            ],
            "expandRandomPassiveSkill": [],
            "randomNum": 0
        },
        {
            "expandId": 2801501,
            "expandPassiveSkill": [
                6000030,
                6000040
            ],
            "expandRandomPassiveSkill": [],
            "randomNum": 0
        },
        {
            "expandId": 2801502,
            "expandPassiveSkill": [
                6000010,
                6000020
            ],
            "expandRandomPassiveSkill": [],
            "randomNum": 0
        },
        {
            "expandId": 2801503,
            "expandPassiveSkill": [
                6000020,
                6000030
            ],
            "expandRandomPassiveSkill": [],
            "randomNum": 0
        },
        {
            "expandId": 2802301,
            "expandPassiveSkill": [
                6000050,
                6000060
            ],
            "expandRandomPassiveSkill": [],
            "randomNum": 0
        },
        {
            "expandId": 2802302,
            "expandPassiveSkill": [
                6000050,
                6000080
            ],
            "expandRandomPassiveSkill": [],
            "randomNum": 0
        },
        {
            "expandId": 2802303,
            "expandPassiveSkill": [
                6000060,
                6000070
            ],
            "expandRandomPassiveSkill": [],
            "randomNum": 0
        },
        {
            "expandId": 2802304,
            "expandPassiveSkill": [
                6000060,
                6000080
            ],
            "expandRandomPassiveSkill": [],
            "randomNum": 0
        },
        {
            "expandId": 2802501,
            "expandPassiveSkill": [
                6000050,
                6000080
            ],
            "expandRandomPassiveSkill": [],
            "randomNum": 0
        },
        {
            "expandId": 2802502,
            "expandPassiveSkill": [
                6000060,
                6000070
            ],
            "expandRandomPassiveSkill": [],
            "randomNum": 0
        },
        {
            "expandId": 2802503,
            "expandPassiveSkill": [
                6000050,
                6000060
            ],
            "expandRandomPassiveSkill": [],
            "randomNum": 0
        },
        {
            "expandId": 2802504,
            "expandPassiveSkill": [
                6000060,
                6000080
            ],
            "expandRandomPassiveSkill": [],
            "randomNum": 0
        },
        {
            "expandId": 2810301,
            "expandPassiveSkill": [
                6000030,
                6000040
            ],
            "expandRandomPassiveSkill": [],
            "randomNum": 0
        },
        {
            "expandId": 2810302,
            "expandPassiveSkill": [
                6000020
            ],
            "expandRandomPassiveSkill": [],
            "randomNum": 0
        },
        {
            "expandId": 2810303,
            "expandPassiveSkill": [
                6000030
            ],
            "expandRandomPassiveSkill": [],
            "randomNum": 0
        },
        {
            "expandId": 2810304,
            "expandPassiveSkill": [
                6000010
            ],
            "expandRandomPassiveSkill": [],
            "randomNum": 0
        }
    ]
}