{
    "data": [
        {
            "id": 1,
            "name": "闪电",
            "spine": "Groza",
            "playeratt": 50.0,
            "playerattName": "中等",
            "playerspd": 10.0,
            "playerspdName": "中等",
            "playeras": 2.0,
            "playerasName": "中等",
            "hp": 3.0,
            "ballisticSpeed": 10.0,
            "linearDrag": 1.0,
            "proAngle": 10.0,
            "projectiles": 1.0,
            "shootRange": 1.5,
            "bulletSize": 1.0,
            "impulse": 1.0,
            "repelSize": 3.0,
            "ui": "Avatar_Head_GrozaSR_Spine",
            "uicode": "GrozaSR"
        },
        {
            "id": 2,
            "name": "托洛洛",
            "spine": "Tololo",
            "playeratt": 30.0,
            "playerattName": "较低",
            "playerspd": 8.0,
            "playerspdName": "中等",
            "playeras": 3.0,
            "playerasName": "高",
            "hp": 3.0,
            "ballisticSpeed": 15.0,
            "linearDrag": 1.0,
            "proAngle": 10.0,
            "projectiles": 2.0,
            "shootRange": 1.5,
            "bulletSize": 1.0,
            "impulse": 1.0,
            "repelSize": 3.0,
            "ui": "Avatar_Head_TololoSSR_Spine",
            "uicode": "TololoSSR"
        },
        {
            "id": 3,
            "name": "纳美西丝",
            "spine": "Nemesis",
            "playeratt": 100.0,
            "playerattName": "高",
            "playerspd": 7.0,
            "playerspdName": "较慢",
            "playeras": 1.0,
            "playerasName": "慢",
            "hp": 3.0,
            "ballisticSpeed": 10.0,
            "linearDrag": 1.0,
            "proAngle": 10.0,
            "projectiles": 1.0,
            "shootRange": 1.5,
            "bulletSize": 1.0,
            "impulse": 1.0,
            "repelSize": 3.0,
            "ui": "Avatar_Head_NemesisSR_Spine",
            "uicode": "NemesisSR"
        }
    ]
}