{
    "data": [
        {
            "system": 1,
            "id": [
                10001
            ]
        },
        {
            "system": 2,
            "id": [
                20001,
                20002,
                20003,
                20004,
                20005,
                20006,
                20007,
                20008,
                20009,
                20010,
                20011,
                20012,
                20013,
                20014,
                20015,
                20016,
                20017,
                20018,
                20019,
                20020,
                20021,
                20022,
                20023,
                20024,
                20025,
                20026,
                20027,
                20028,
                20029,
                20030,
                20031,
                20032,
                20033,
                20034,
                20035,
                20036,
                20037,
                20038,
                20039,
                20040,
                20041,
                20042,
                20043,
                20044,
                20045,
                20046,
                20047,
                20048,
                20049,
                20050,
                20051,
                20052,
                20053,
                20054,
                20055,
                20056,
                20057,
                20058,
                20059,
                20060,
                20061,
                20062,
                20063,
                20064,
                20065,
                20066,
                20067,
                20068,
                20069,
                20070,
                20071,
                20072,
                20073,
                20074,
                20075,
                20076,
                20077,
                20078,
                20079,
                20080,
                20081,
                20082,
                20083,
                20084,
                20085,
                20086,
                20087,
                20088,
                20089,
                20090,
                20091,
                20092,
                20093,
                20094,
                20095,
                20096,
                20097,
                20098,
                20099,
                20100,
                20101,
                20102,
                20103,
                20104,
                20105,
                20106,
                20107,
                20108,
                20109,
                20110,
                20111,
                20112,
                20113,
                20114,
                20115,
                20116,
                20117,
                20118,
                20119
            ]
        },
        {
            "system": 3,
            "id": [
                30001,
                30002,
                30003,
                30004,
                30005,
                30006,
                30007,
                30008,
                30009,
                30010,
                30011,
                30012
            ]
        },
        {
            "system": 4,
            "id": [
                40001,
                40002,
                40003,
                40004
            ]
        },
        {
            "system": 5,
            "id": [
                50001,
                50002,
                50003,
                50004,
                50005,
                50006,
                51001,
                51002
            ]
        },
        {
            "system": 7,
            "id": [
                70001,
                70002
            ]
        },
        {
            "system": 8,
            "id": [
                80001,
                80002,
                80003,
                80004,
                80005,
                80006,
                80007,
                80008,
                80009,
                80010,
                80011,
                80012,
                80013,
                80014,
                80015,
                80016,
                80017,
                80018,
                80019,
                80020,
                80021,
                80022,
                80023,
                80024
            ]
        },
        {
            "system": 9,
            "id": [
                90001,
                90002,
                90003,
                90004,
                90005,
                90006,
                90007,
                90008,
                90009,
                90010,
                90011,
                90012
            ]
        },
        {
            "system": 99,
            "id": [
                990001
            ]
        }
    ]
}